README.rst
setup.py
myrollingforecastpackagem/Rollingpredict.py
myrollingforecastpackagem/__init__.py
myrollingforecastpackagem.egg-info/PKG-INFO
myrollingforecastpackagem.egg-info/SOURCES.txt
myrollingforecastpackagem.egg-info/dependency_links.txt
myrollingforecastpackagem.egg-info/entry_points.txt
myrollingforecastpackagem.egg-info/requires.txt
myrollingforecastpackagem.egg-info/top_level.txt